{
    "schemaVersion": 1,
    "metadata": {
        "plugin": "manual-sorting",
        "version": "1.0.0",
        "title": "Manual Sorting",
        "description": "拖放文件排序。",
        "language": "zh-cn",
        "supportedVersions": "3.2.4",
        "author": "Anonym0usPlayer"
    },
    "dict": {
        "main.js": {
            "ast": [
                {
                    "type": "CallExpression",
                    "name": "info",
                    "source": "Drag started",
                    "target": "拖拽开始"
                },
                {
                    "type": "CallExpression",
                    "name": "info",
                    "source": "Drag and drop enabled",
                    "target": "拖放已启用"
                },
                {
                    "type": "CallExpression",
                    "name": "info",
                    "source": "Drag and drop disabled",
                    "target": "拖放已禁用"
                },
                {
                    "type": "CallExpression",
                    "name": "info",
                    "source": "Refreshing Explorer after mount",
                    "target": "挂载后刷新资源管理器"
                },
                {
                    "type": "CallExpression",
                    "name": "info",
                    "source": "Explorer already mounted",
                    "target": "资源管理器已挂载"
                },
                {
                    "type": "CallExpression",
                    "name": "info",
                    "source": "Explorer mounted",
                    "target": "资源管理器已挂载"
                },
                {
                    "type": "CallExpression",
                    "name": "info",
                    "source": "Directory did not change, calling sort on File Explorer manually",
                    "target": "目录未更改，手动对文件资源管理器进行排序"
                },
                {
                    "type": "CallExpression",
                    "name": "info",
                    "source": "Updating order...",
                    "target": "正在更新排序..."
                },
                {
                    "type": "CallExpression",
                    "name": "info",
                    "source": "Explorer unpatched",
                    "target": "资源管理器已取消补丁"
                },
                {
                    "type": "CallExpression",
                    "name": "info",
                    "source": "Sort order menu unpatched",
                    "target": "排序菜单已取消补丁"
                },
                {
                    "type": "CallExpression",
                    "name": "info",
                    "source": "Manual Sorting unloaded",
                    "target": "手动排序卸载"
                },
                {
                    "type": "CallExpression",
                    "name": "info",
                    "source": "Migrating settings to v4 format",
                    "target": "设置迁移至v4格式"
                },
                {
                    "type": "CallExpression",
                    "name": "info",
                    "source": "Settings loaded:",
                    "target": "设置加载："
                },
                {
                    "type": "CallExpression",
                    "name": "info",
                    "source": "Settings saved:",
                    "target": "设置保存："
                },
                {
                    "type": "CallExpression",
                    "name": "setDesc",
                    "source": "Show debug logs in the console.",
                    "target": "在控制台中显示调试日志。"
                },
                {
                    "type": "CallExpression",
                    "name": "setDesc",
                    "source": "Default new item placement.",
                    "target": "默认新项目放置位置。"
                },
                {
                    "type": "CallExpression",
                    "name": "setName",
                    "source": "Debug Mode",
                    "target": "调试模式"
                },
                {
                    "type": "CallExpression",
                    "name": "setName",
                    "source": "New item placement",
                    "target": "新建项位置"
                },
                {
                    "type": "CallExpression",
                    "name": "setTitle",
                    "source": "Manual Sorting",
                    "target": "手动排序"
                },
                {
                    "type": "CallExpression",
                    "name": "setTitle",
                    "source": "Manual sorting",
                    "target": "手动排序"
                },
                {
                    "type": "CallExpression",
                    "name": "setTitle",
                    "source": "Reset order",
                    "target": "重置顺序"
                },
                {
                    "type": "CallExpression",
                    "name": "setButtonText",
                    "source": "Yep",
                    "target": "确认"
                },
                {
                    "type": "CallExpression",
                    "name": "setButtonText",
                    "source": "Cancel",
                    "target": "取消"
                },
                {
                    "type": "CallExpression",
                    "name": "warn",
                    "source": "Settings changed externally",
                    "target": "设置已在外部被更改"
                },
                {
                    "type": "ObjectProperty",
                    "name": "text",
                    "source": "Reset custom order?",
                    "target": "是否重置自定义顺序？"
                }
            ],
            "regex": [
                {
                    "source": "setName(`Debug Mode`)",
                    "target": "setName(`调试模式`)"
                },
                {
                    "source": "setName(`New item placement`)",
                    "target": "setName(`新建项位置`)"
                },
                {
                    "source": "setDesc(`Show debug logs in the console.`)",
                    "target": "setDesc(`在控制台中显示调试日志。`)"
                },
                {
                    "source": "setDesc(`Default new item placement.`)",
                    "target": "setDesc(`默认新项目放置位置。`)"
                },
                {
                    "source": "setTitle(`Manual Sorting`)",
                    "target": "setTitle(`手动排序`)"
                },
                {
                    "source": "setTitle(`Manual sorting`)",
                    "target": "setTitle(`手动排序`)"
                },
                {
                    "source": "setTitle(`Reset order`)",
                    "target": "setTitle(`重置顺序`)"
                },
                {
                    "source": "setButtonText(`Yep`)",
                    "target": "setButtonText(`确认`)"
                },
                {
                    "source": "setButtonText(`Cancel`)",
                    "target": "setButtonText(`取消`)"
                },
                {
                    "source": "text:`Reset custom order?`",
                    "target": "text:`是否重置自定义顺序？`"
                }
            ]
        }
    }
}